verkefni/__init__.py
verkefni/common.py
verkefni/job.py
verkefni/task.py
verkefni/tasker.py
verkefni/worker.py
verkefni-0.1.1.data/scripts/configure
verkefni-0.1.1.data/scripts/log
verkefni-0.1.1.data/scripts/monitor
verkefni-0.1.1.data/scripts/tasker
verkefni-0.1.1.data/scripts/worker-arithmetic
verkefni-0.1.1.data/scripts/worker-lexical
verkefni-0.1.1.dist-info/METADATA
verkefni-0.1.1.dist-info/WHEEL
verkefni-0.1.1.dist-info/top_level.txt
verkefni-0.1.1.dist-info/RECORD
