Metadata-Version: 2.1
Name: verkefni
Version: 0.1.1
Summary: Efficient execution of trees of dependent tasks
Home-page: http://gitlab.com/OldIronHorse/verkefni
Author: Simon Redding
Author-email: s1m0n.r3dd1ng@gmail.com
License: GPL3
Platform: UNKNOWN
Requires-Python: >=3.10.0
Requires-Dist: click
Requires-Dist: redis
Requires-Dist: pika
